xjam/__init__.py
xjam/libjamio.py
xjam/libjamstd.py
xjam/libjamtdm.py
xjam-2.0.data/scripts/x.jam
xjam-2.0.dist-info/METADATA
xjam-2.0.dist-info/WHEEL
xjam-2.0.dist-info/top_level.txt
xjam-2.0.dist-info/RECORD
