Metadata-Version: 2.1
Name: xjam
Version: 2.0
Summary: Generate stacking layers via the Joining and Arrangement of Multilayers (JAM) notation
Home-page: https://github.com/Theochem-merida/xjam
Author: Jessica Arcudia, Filiberto Ortiz-Chi, and Gabriel Merino
Author-email: fortiz666@gmail.com
License: None
Platform: UNKNOWN
Classifier: Programming Language :: Python :: 3
Classifier: Operating System :: OS Independent
Requires-Python: >=3.5
Requires-Dist: numpy
